{
    "membershipLevels": [
        {
            "level": "Non Profit Organization",
            "levelName" : "NP",
            "cost": 0,
            "benefits": [
                "Access to community events",
                "Basic training sessions",
                "Listing in business directory"
            ]
        },
        {
            "level": "Bronze",
            "levelName" : "B",
            "cost": 150,
            "benefits": [
                "Access to community events",
                "Enhanced business directory listing",
                "Discount on event tickets",
                "Participation in training programs"
            ]
        },
        {
            "level": "Silver",
            "levelName" : "S",
            "cost": 350,
            "benefits": [
                "All Bronze-level benefits",
                "Priority business directory listing",
                "Access to member-only events",
                "Discounts on event sponsorships",
                "Participation in special training and webinars",
                "Spotlight on home page (randomly featured)"
            ]
        },
        {
            "level": "Gold",
            "levelName" : "G",
            "cost": 500,
            "benefits": [
                "All Silver-level benefits",
                "Premium business directory listing",
                "Guaranteed spotlight on home page",
                "Exclusive advertising opportunities",
                "Free event tickets for major events",
                "First access to sponsorships",
                "Invitations to VIP events"
            ]
        }
    ]
}